{
  "1989": {
    "genres": {
      "adult standards": 10,
      "album rock": 25,
      "art rock": 10,
      "classic rock": 18,
      "folk": 3,
      "folk rock": 2,
      "mellow gold": 28,
      "pop christmas": 14,
      "rock": 24,
      "roots rock": 2,
      "singer-songwriter": 5,
      "soft rock": 33,
      "funk": 9,
      "hip pop": 7,
      "new jack swing": 12,
      "quiet storm": 14,
      "r&b": 14,
      "urban contemporary": 20,
      "glam metal": 15,
      "hard rock": 18,
      "metal": 7,
      "dance pop": 18,
      "dance rock": 23,
      "freestyle": 17,
      "new romantic": 22,
      "new wave": 14,
      "new wave pop": 38,
      "neo soul": 3,
      "pop": 10,
      "pop rap": 1,
      "soul": 4,
      "brill building pop": 2,
      "cabaret": 2,
      "christmas": 2,
      "hollywood": 2,
      "lounge": 2,
      "show tunes": 1,
      "vocal jazz": 2,
      "boy band": 8,
      "latin": 1,
      "latin christmas": 1,
      "latin pop": 1,
      "spanish pop": 1,
      "tropical": 1,
      "europop": 9,
      "pop rock": 7,
      "swedish pop": 2,
      "synthpop": 7,
      "alternative rock": 9,
      "heavy christmas": 6,
      "post-grunge": 7,
      "post-teen pop": 7,
      "soul christmas": 11,
      "jangle pop": 3,
      "hip hop": 3,
      "hip house": 5,
      "rap": 3,
      "disco": 7,
      "gangster rap": 1,
      "post-disco": 2,
      "dream pop": 1,
      "gothic rock": 1,
      "neo-psychedelic": 1,
      "post-punk": 1,
      "uk post-punk": 2,
      "blues-rock": 4,
      "bubblegum pop": 1,
      "movie tunes": 1,
      "permanent wave": 3,
      "classic funk rock": 3,
      "jazz blues": 1,
      "jazz christmas": 1,
      "motown": 3,
      "soul blues": 1,
      "funk rock": 4,
      "indie rock": 2,
      "british blues": 1,
      "electric blues": 1,
      "modern blues": 1,
      "southern rock": 4,
      "texas blues": 1,
      "alternative metal": 2,
      "j-poprock": 1,
      "folk christmas": 1,
      "folk-pop": 1,
      "sleaze rock": 1,
      "lilith": 1,
      "glam rock": 1,
      "protopunk": 1,
      "psychedelic rock": 1
    },
    "events": "<ul>\n<li>\n<a href=\"/wiki/January_14\" title=\"January 14\">January 14</a> – <a href=\"/wiki/Paul_McCartney\" title=\"Paul McCartney\">Paul McCartney</a> releases <i><a href=\"/wiki/%D0%A1%D0%BD%D0%BE%D0%B2%D0%B0_%D0%B2_%D0%A1%D0%A1%D0%A1%D0%A0\" class=\"mw-redirect\" title=\"Снова в СССР\">Снова в СССР</a></i> (<i>Back in the USSR</i>) exclusively in the <a href=\"/wiki/Soviet_Union\" title=\"Soviet Union\">USSR</a>. <a href=\"/wiki/Bootleg_recording\" title=\"Bootleg recording\">Bootleg</a> copies sell for as much as US$1,000 in the United States.</li>\n<li>\n<a href=\"/wiki/January_23\" title=\"January 23\">January 23</a> – <a href=\"/wiki/James_Brown\" title=\"James Brown\">James Brown</a> is sentenced in <a href=\"/wiki/Georgia_(U.S._state)\" title=\"Georgia (U.S. state)\">Georgia</a>, USA, to six years in jail in connection with a police chase through two different states.</li>\n<li>\n<a href=\"/wiki/January_25\" title=\"January 25\">January 25</a> – <a href=\"/wiki/Madonna_(entertainer)\" title=\"Madonna (entertainer)\">Madonna</a> files for divorce from <a href=\"/wiki/Sean_Penn\" title=\"Sean Penn\">Sean Penn</a> after three-and-a-half years of marriage, citing irreconcilable differences.</li>\n<li>\n<a href=\"/wiki/January_27\" title=\"January 27\">January 27</a> – <a href=\"/wiki/Michael_Jackson\" title=\"Michael Jackson\">Michael Jackson</a> ends the Bad World Tour in Los Angeles, USA.</li>\n<li>\n<a href=\"/wiki/February_12\" title=\"February 12\">February 12</a>\n<ul>\n<li>\n<a href=\"/wiki/Roy_Orbison\" title=\"Roy Orbison\">Roy Orbison</a> joins <a href=\"/wiki/Elvis_Presley\" title=\"Elvis Presley\">Elvis Presley</a> as the only singers to ever simultaneously have two top 5 albums on the <a href=\"/wiki/Billboard_charts\" title=\"Billboard charts\">Billboard charts</a>.</li>\n<li>\n<a href=\"/wiki/Tiny_Tim_(musician)\" title=\"Tiny Tim (musician)\">Tiny Tim</a> launches an unsuccessful campaign to be elected mayor of New York City, USA.</li>\n</ul>\n</li>\n<li>\n<a href=\"/wiki/February_17\" title=\"February 17\">February 17</a> – <a href=\"/wiki/Whitesnake\" title=\"Whitesnake\">Whitesnake</a>'s <a href=\"/wiki/David_Coverdale\" title=\"David Coverdale\">David Coverdale</a> marries <a href=\"/wiki/Tawny_Kitaen\" title=\"Tawny Kitaen\">Tawny Kitaen</a>.</li>\n<li>\n<a href=\"/wiki/March_21\" title=\"March 21\">March 21</a> – <a href=\"/wiki/Madonna_(entertainer)\" title=\"Madonna (entertainer)\">Madonna</a>'s \"<a href=\"/wiki/Like_a_Prayer_(song)\" title=\"Like a Prayer (song)\">Like a Prayer</a>\" music video, taped in late December 1988, attracts criticism for its use of Catholic Church iconography and for the use of <a href=\"/wiki/Cross_burning\" title=\"Cross burning\">cross burning</a> imagery, but also garners praise for its interpretation of discrimination, rape, and <a href=\"/wiki/Faith\" title=\"Faith\">faith</a>. <a href=\"/wiki/Pepsi\" title=\"Pepsi\">Pepsi</a> drops Madonna as a spokesperson out of fear the video will cause religious groups to <a href=\"/wiki/Boycott\" title=\"Boycott\">boycott</a> the company.</li>\n<li>\n<a href=\"/wiki/April_9\" title=\"April 9\">April 9</a> – <a href=\"/wiki/The_Rolling_Stones\" title=\"The Rolling Stones\">The Rolling Stones</a>' <a href=\"/wiki/Bill_Wyman\" title=\"Bill Wyman\">Bill Wyman</a> announces that he will marry 19-year-old <a href=\"/wiki/Mandy_Smith\" title=\"Mandy Smith\">Mandy Smith</a>, his girlfriend for six years.</li>\n<li>\n<a href=\"/wiki/April_12\" title=\"April 12\">April 12</a> – <a href=\"/wiki/Michael_Jackson\" title=\"Michael Jackson\">Michael Jackson</a> is named \"<a href=\"/wiki/Honorific_nicknames_in_popular_music\" title=\"Honorific nicknames in popular music\">King of Pop</a>\" after receiving the Soul Train Heritage Awards.</li>\n<li>\n<a href=\"/wiki/April_28\" title=\"April 28\">April 28</a> – <a href=\"/wiki/Jon_Bon_Jovi\" title=\"Jon Bon Jovi\">Jon Bon Jovi</a> marries his high school sweetheart Dorothea Hurley at the <a href=\"/wiki/Graceland_Wedding_Chapel\" title=\"Graceland Wedding Chapel\">Graceland Wedding Chapel</a> in <a href=\"/wiki/Las_Vegas,_Nevada\" class=\"mw-redirect\" title=\"Las Vegas, Nevada\">Las Vegas, Nevada</a>, USA.</li>\n<li>\n<a href=\"/wiki/May_1\" title=\"May 1\">May 1</a> – California, USA jewelry store employees called the police reporting a suspicious person hanging around their store. The person turns out to be <a href=\"/wiki/Michael_Jackson\" title=\"Michael Jackson\">Michael Jackson</a> shopping in disguise.</li>\n<li>\n<a href=\"/wiki/July_9\" title=\"July 9\">July 9</a> – All four original members of <a href=\"/wiki/The_Monkees\" title=\"The Monkees\">The Monkees</a> reunite in Los Angeles, USA, for a concert performance at the <a href=\"/wiki/Universal_Amphitheatre\" title=\"Universal Amphitheatre\">Universal Amphitheatre</a>. The following day the quartet attend an induction ceremony at the <a href=\"/wiki/Hollywood_Walk_of_Fame\" title=\"Hollywood Walk of Fame\">Hollywood Walk of Fame</a>, where they receive a star.</li>\n<li>\n<a href=\"/wiki/July_23\" title=\"July 23\">July 23</a> – Former <a href=\"/wiki/The_Beatles\" title=\"The Beatles\">Beatle</a> <a href=\"/wiki/Ringo_Starr\" title=\"Ringo Starr\">Ringo Starr</a> forms his own band named <a href=\"/wiki/Ringo_Starr_%26_His_All-Starr_Band\" title=\"Ringo Starr &amp; His All-Starr Band\">Ringo Starr &amp; His All-Starr Band</a>.</li>\n<li>\n<a href=\"/wiki/August_3\" title=\"August 3\">August 3</a> – <a href=\"/wiki/Sergio_Franchi\" title=\"Sergio Franchi\">Sergio Franchi</a> collapses before scheduled concert; dies 9 months later of brain cancer.</li>\n<li>\n<a href=\"/wiki/August_11\" title=\"August 11\">August 11</a> – 12 – The <a href=\"/wiki/Moscow_Music_Peace_Festival\" title=\"Moscow Music Peace Festival\">Moscow Music Peace Festival</a> is held in the Soviet Union. The event is put together by <a href=\"/wiki/Doc_McGhee\" title=\"Doc McGhee\">Doc McGhee</a> and the <a href=\"/wiki/Make-A-Wish_Foundation\" title=\"Make-A-Wish Foundation\">Make-A-Wish Foundation</a> and headline acts include <a href=\"/wiki/Bon_Jovi\" title=\"Bon Jovi\">Bon Jovi</a>, <a href=\"/wiki/Ozzy_Osbourne\" title=\"Ozzy Osbourne\">Ozzy Osbourne</a>, <a href=\"/wiki/M%C3%B6tley_Cr%C3%BCe\" title=\"Mötley Crüe\">Mötley Crüe</a>, <a href=\"/wiki/Skid_Row_(American_band)\" title=\"Skid Row (American band)\">Skid Row</a>, <a href=\"/wiki/Cinderella_(band)\" title=\"Cinderella (band)\">Cinderella</a>, and the <a href=\"/wiki/Scorpions_(band)\" title=\"Scorpions (band)\">Scorpions</a>.</li>\n<li>\n<a href=\"/wiki/August_31\" title=\"August 31\">August 31</a> – <a href=\"/wiki/The_Rolling_Stones\" title=\"The Rolling Stones\">The Rolling Stones</a> open their <i><a href=\"/wiki/Steel_Wheels\" title=\"Steel Wheels\">Steel Wheels</a></i> North American tour in <a href=\"/wiki/Philadelphia\" title=\"Philadelphia\">Philadelphia</a>, USA.</li>\n<li>\n<a href=\"/wiki/September_9\" title=\"September 9\">September 9</a>\n<ul>\n<li>The <a href=\"/wiki/Morton_H._Meyerson_Symphony_Center\" title=\"Morton H. Meyerson Symphony Center\">Morton H. Meyerson Symphony Center</a>, designed by <a href=\"/wiki/I._M._Pei\" title=\"I. M. Pei\">I. M. Pei</a>, opens in <a href=\"/wiki/Dallas,_Texas\" class=\"mw-redirect\" title=\"Dallas, Texas\">Dallas, Texas</a>, USA.<sup id=\"cite_ref-1\" class=\"reference\"><a href=\"#cite_note-1\">[1]</a></sup>\n</li>\n<li>\n<a href=\"/wiki/Madonna_(entertainer)\" title=\"Madonna (entertainer)\">Madonna</a> gives a risqué performance at the <a href=\"/wiki/1989_MTV_Video_Music_Awards\" title=\"1989 MTV Video Music Awards\">1989 MTV Video Music Awards</a>. Clad in baggy black sweatpants and a black bustier, she rocks the audience by simulating <a href=\"/wiki/Masturbation\" title=\"Masturbation\">masturbation</a>. The version of the song used in the show would later serve as the opening number of 1990's \"<a href=\"/wiki/Blond_Ambition_World_Tour\" title=\"Blond Ambition World Tour\">Blond Ambition World Tour</a>\".</li>\n</ul>\n</li>\n<li>\n<a href=\"/wiki/September_14\" title=\"September 14\">September 14</a> – Madonna is granted a divorce from Sean Penn.</li>\n<li>\n<a href=\"/wiki/October_15\" title=\"October 15\">October 15</a> – <a href=\"/wiki/Media_Rings\" title=\"Media Rings\">Media Rings</a> Corporation, the Japanese music, video game, and software publishing company, is founded in Akasaka.</li>\n<li>\n<a href=\"/wiki/December_23\" title=\"December 23\">December 23</a> – <a href=\"/wiki/Ice_Cube\" title=\"Ice Cube\">Ice Cube</a> leaves <a href=\"/wiki/N.W.A\" title=\"N.W.A\">N.W.A</a> after financial problems and several conflicts with their manager <a href=\"/wiki/Jerry_Heller\" title=\"Jerry Heller\">Jerry Heller</a> and the group's founder <a href=\"/wiki/Eazy-E\" title=\"Eazy-E\">Eazy-E</a>. By this time, Cube has been recording his <a href=\"/wiki/AmeriKKKa%27s_Most_Wanted\" title=\"AmeriKKKa's Most Wanted\">solo debut album</a>, which will be released next year.</li>\n</ul>",
    "avg_tempo": 122.8112588235294,
    "avg_valence": 0.5968117647058825,
    "songs": [
      {
        "artist": "Chicago",
        "track": "Look Away",
        "spotify_artist": "Chicago",
        "spotify_track": "Look Away",
        "time_sig": 4,
        "tempo": 172.986,
        "valence": 0.173,
        "mode": 1,
        "key": 9,
        "energy": 0.569,
        "duration": 241333,
        "genres": [
          "adult standards",
          "album rock",
          "art rock",
          "classic rock",
          "folk",
          "folk rock",
          "mellow gold",
          "pop christmas",
          "rock",
          "roots rock",
          "singer-songwriter",
          "soft rock"
        ],
        "popularity": 30,
        "preview": "https://p.scdn.co/mp3-preview/b5e8d1dccff70f95a2b9a6b534b701a164f1e1f5"
      },
      {
        "artist": "Bobby Brown",
        "track": "My Prerogative",
        "spotify_artist": "Bobby Brown",
        "spotify_track": "My Prerogative",
        "time_sig": 4,
        "tempo": 110.163,
        "valence": 0.694,
        "mode": 1,
        "key": 9,
        "energy": 0.625,
        "duration": 291560,
        "genres": [
          "funk",
          "hip pop",
          "new jack swing",
          "quiet storm",
          "r&b",
          "urban contemporary"
        ],
        "popularity": 45,
        "preview": "https://p.scdn.co/mp3-preview/b02b53cb9d2210eb93cb48f78bbba9cac60f32a5"
      },
      {
        "artist": "Poison",
        "track": "Every Rose Has Its Thorn",
        "spotify_artist": "Poison",
        "spotify_track": "Every Rose Has Its Thorn - 2003 - Remaster",
        "time_sig": 4,
        "tempo": 140.203,
        "valence": 0.295,
        "mode": 1,
        "key": 6,
        "energy": 0.635,
        "duration": 260160,
        "genres": [
          "album rock",
          "classic rock",
          "glam metal",
          "hard rock",
          "metal",
          "rock"
        ],
        "popularity": 57,
        "preview": "https://p.scdn.co/mp3-preview/73c5fb4a24773c791a0f8f6ac7b45bf0352b4c22"
      },
      {
        "artist": "Paula Abdul",
        "track": "Straight Up",
        "spotify_artist": "Paula Abdul",
        "spotify_track": "Straight Up",
        "time_sig": 4,
        "tempo": 95.862,
        "valence": 0.752,
        "mode": 1,
        "key": 7,
        "energy": 0.826,
        "duration": 250032,
        "genres": [
          "dance pop",
          "dance rock",
          "freestyle",
          "new romantic",
          "new wave",
          "new wave pop",
          "soft rock",
          "urban contemporary"
        ],
        "popularity": 54,
        "preview": "https://p.scdn.co/mp3-preview/2aef58727efcc1ae26122988259e96a7e6be397d"
      },
      {
        "artist": "Janet Jackson",
        "track": "Miss You Much",
        "spotify_artist": "Janet Jackson",
        "spotify_track": "Miss You Much",
        "time_sig": 4,
        "tempo": 115.19,
        "valence": 0.64,
        "mode": 0,
        "key": 6,
        "energy": 0.975,
        "duration": 252333,
        "genres": [
          "dance pop",
          "hip pop",
          "neo soul",
          "new jack swing",
          "pop",
          "pop rap",
          "quiet storm",
          "r&b",
          "soul",
          "urban contemporary"
        ],
        "popularity": 40,
        "preview": "https://p.scdn.co/mp3-preview/e7c7019a238bf2a98e2a9f19c0043aeb19c7d926"
      },
      {
        "artist": "Paula Abdul",
        "track": "Cold Hearted",
        "spotify_artist": "Paula Abdul",
        "spotify_track": "Cold Hearted",
        "time_sig": 4,
        "tempo": 122.38,
        "valence": 0.72,
        "mode": 0,
        "key": 7,
        "energy": 0.679,
        "duration": 230853,
        "genres": [
          "dance pop",
          "dance rock",
          "freestyle",
          "new romantic",
          "new wave",
          "new wave pop",
          "soft rock",
          "urban contemporary"
        ],
        "popularity": 46,
        "preview": "https://p.scdn.co/mp3-preview/0115e602f170e642fe3c1259650ab38fd3c8a0fc"
      },
      {
        "artist": "Bette Midler",
        "track": "Wind Beneath My Wings",
        "spotify_artist": "Bette Midler",
        "spotify_track": "Wind Beneath My Wings",
        "time_sig": 4,
        "tempo": 123.694,
        "valence": 0.173,
        "mode": 1,
        "key": 10,
        "energy": 0.458,
        "duration": 293853,
        "genres": [
          "adult standards",
          "brill building pop",
          "cabaret",
          "christmas",
          "folk",
          "hollywood",
          "lounge",
          "mellow gold",
          "new wave pop",
          "show tunes",
          "singer-songwriter",
          "soft rock",
          "vocal jazz"
        ],
        "popularity": 51,
        "preview": "https://p.scdn.co/mp3-preview/e202bdfd8169b84f0877e20c6d33be494130ecaf"
      },
      {
        "artist": "Milli Vanilli",
        "track": "Girl You Know Its True",
        "spotify_artist": "Milli Vanilli",
        "spotify_track": "Girl You Know It's True",
        "time_sig": 4,
        "tempo": 97.718,
        "valence": 0.529,
        "mode": 0,
        "key": 10,
        "energy": 0.822,
        "duration": 198573,
        "genres": [
          "boy band",
          "freestyle",
          "new wave pop"
        ],
        "popularity": 48,
        "preview": "https://p.scdn.co/mp3-preview/cba566b01ba672fc143dcfaa3945c99bd594a60f"
      },
      {
        "artist": "Will To Power",
        "track": "Baby, I Love Your Way-Freebird",
        "spotify_artist": "Will To Power",
        "spotify_track": "Baby, I Love Your Way/Freebird",
        "time_sig": 4,
        "tempo": 150.829,
        "valence": 0.482,
        "mode": 1,
        "key": 7,
        "energy": 0.435,
        "duration": 247200,
        "genres": [
          "freestyle"
        ],
        "popularity": 39,
        "preview": "https://p.scdn.co/mp3-preview/1a2bb02a1e585c2e9c0271ba34c2e113d29acfd8"
      },
      {
        "artist": "Anita Baker",
        "track": "Giving You The Best That I Got"
      },
      {
        "artist": "Richard Marx",
        "track": "Right Here Waiting",
        "spotify_artist": "Richard Marx",
        "spotify_track": "Right Here Waiting",
        "time_sig": 4,
        "tempo": 177.679,
        "valence": 0.125,
        "mode": 1,
        "key": 0,
        "energy": 0.252,
        "duration": 264333,
        "genres": [
          "adult standards",
          "album rock",
          "mellow gold",
          "new romantic",
          "new wave pop",
          "rock",
          "soft rock"
        ],
        "popularity": 64,
        "preview": "https://p.scdn.co/mp3-preview/894e2925f04ed4276f7cdeb0eade5bff4f79fe9a"
      },
      {
        "artist": "Boy Meets Girl",
        "track": "Waiting For A Star To Fall",
        "spotify_artist": "Boy Meets Girl",
        "spotify_track": "Waiting for a Star to Fall",
        "time_sig": 4,
        "tempo": 116.246,
        "valence": 0.589,
        "mode": 1,
        "key": 3,
        "energy": 0.734,
        "duration": 266213,
        "genres": [
          "freestyle",
          "new wave pop",
          "soft rock"
        ],
        "popularity": 52,
        "preview": "https://p.scdn.co/mp3-preview/4a464e568776f4f9b95cd1b09faf1f59125b3904"
      },
      {
        "artist": "Debbie Gibson",
        "track": "Lost In Your Eyes",
        "spotify_artist": "Debbie Gibson",
        "spotify_track": "Lost In Your Eyes",
        "time_sig": 4,
        "tempo": 144.46,
        "valence": 0.228,
        "mode": 1,
        "key": 7,
        "energy": 0.613,
        "duration": 213000,
        "genres": [
          "freestyle",
          "new wave pop",
          "soft rock"
        ],
        "popularity": 49,
        "preview": "https://p.scdn.co/mp3-preview/c6d882be38960697c7db8cbc4084dd7d1e1612cf"
      },
      {
        "artist": "Gloria Estefan",
        "track": "Don’t Wanna Lose You",
        "spotify_artist": "Gloria Estefan",
        "spotify_track": "Don't Wanna Lose You",
        "time_sig": 4,
        "tempo": 164.391,
        "valence": 0.439,
        "mode": 1,
        "key": 5,
        "energy": 0.469,
        "duration": 249133,
        "genres": [
          "adult standards",
          "dance pop",
          "latin",
          "latin christmas",
          "latin pop",
          "new wave pop",
          "pop christmas",
          "spanish pop",
          "tropical"
        ],
        "popularity": 36,
        "preview": "https://p.scdn.co/mp3-preview/8952b197bf474ada13434425a1ea79bbe4293154"
      },
      {
        "artist": "Warrant",
        "track": "Heavan"
      },
      {
        "artist": "Milli Vanilli",
        "track": "Girl I’m Gonna Miss You",
        "spotify_artist": "Milli Vanilli",
        "spotify_track": "I'm Gonna Miss You",
        "time_sig": 4,
        "tempo": 151.239,
        "valence": 0.767,
        "mode": 1,
        "key": 9,
        "energy": 0.453,
        "duration": 238840,
        "genres": [
          "boy band",
          "freestyle",
          "new wave pop"
        ],
        "popularity": 29,
        "preview": "https://p.scdn.co/mp3-preview/4e18b659fac09444c6e0e145f2c5c05c45e7bf12"
      },
      {
        "artist": "Roxette",
        "track": "The Look",
        "spotify_artist": "Roxette",
        "spotify_track": "The Look",
        "time_sig": 4,
        "tempo": 95.011,
        "valence": 0.535,
        "mode": 1,
        "key": 2,
        "energy": 0.838,
        "duration": 237320,
        "genres": [
          "dance pop",
          "dance rock",
          "europop",
          "new romantic",
          "new wave pop",
          "pop christmas",
          "pop rock",
          "rock",
          "soft rock",
          "swedish pop"
        ],
        "popularity": 61,
        "preview": "https://p.scdn.co/mp3-preview/d7698dbbf903869aeecc6cd749b1eed113adf71c"
      },
      {
        "artist": "Fine Young Cannibals",
        "track": "She Drives Me Crazy",
        "spotify_artist": "Fine Young Cannibals",
        "spotify_track": "She Drives Me Crazy",
        "time_sig": 4,
        "tempo": 108.799,
        "valence": 0.962,
        "mode": 1,
        "key": 2,
        "energy": 0.694,
        "duration": 215347,
        "genres": [
          "art rock",
          "dance rock",
          "mellow gold",
          "new romantic",
          "new wave",
          "new wave pop",
          "soft rock",
          "synthpop"
        ],
        "popularity": 55,
        "preview": "https://p.scdn.co/mp3-preview/450d16ac9e03f7a96cd953061a356facf64e3a4c"
      },
      {
        "artist": "Bobby Brown",
        "track": "On Our Own",
        "spotify_artist": "Bobby Brown",
        "spotify_track": "On Our Own",
        "time_sig": 4,
        "tempo": 101.805,
        "valence": 0.57,
        "mode": 1,
        "key": 2,
        "energy": 0.904,
        "duration": 294413,
        "genres": [
          "funk",
          "hip pop",
          "new jack swing",
          "quiet storm",
          "r&b",
          "urban contemporary"
        ],
        "popularity": 33,
        "preview": "https://p.scdn.co/mp3-preview/e4b65fdc461b3f613eddc37524fc166a5975a935"
      },
      {
        "artist": "Phil Collins",
        "track": "Two Hearts",
        "spotify_artist": "Phil Collins",
        "spotify_track": "Two Hearts - 2016 Remastered",
        "time_sig": 4,
        "tempo": 155.546,
        "valence": 0.731,
        "mode": 1,
        "key": 7,
        "energy": 0.912,
        "duration": 204253,
        "genres": [
          "adult standards",
          "album rock",
          "art rock",
          "classic rock",
          "dance rock",
          "hard rock",
          "mellow gold",
          "new romantic",
          "new wave pop",
          "rock",
          "singer-songwriter",
          "soft rock"
        ],
        "popularity": 20,
        "preview": "https://p.scdn.co/mp3-preview/b74b1ad0a492892dfeea59d70aa4fde553b401de"
      },
      {
        "artist": "Milli Vanilli",
        "track": "Blame It On The Rain",
        "spotify_artist": "Milli Vanilli",
        "spotify_track": "Blame It on the Rain",
        "time_sig": 4,
        "tempo": 97.515,
        "valence": 0.508,
        "mode": 0,
        "key": 4,
        "energy": 0.827,
        "duration": 248533,
        "genres": [
          "boy band",
          "freestyle",
          "new wave pop"
        ],
        "popularity": 37,
        "preview": "https://p.scdn.co/mp3-preview/2c5217d8957d15c2f177e0ab21f2a7450dc0be2c"
      },
      {
        "artist": "Roxette",
        "track": "Listen To Your Heart",
        "spotify_artist": "Roxette",
        "spotify_track": "Listen To Your Heart",
        "time_sig": 4,
        "tempo": 86.063,
        "valence": 0.331,
        "mode": 0,
        "key": 1,
        "energy": 0.583,
        "duration": 328093,
        "genres": [
          "dance pop",
          "dance rock",
          "europop",
          "new romantic",
          "new wave pop",
          "pop christmas",
          "pop rock",
          "rock",
          "soft rock",
          "swedish pop"
        ],
        "popularity": 61,
        "preview": "https://p.scdn.co/mp3-preview/0e4f8623b2ed598773d6a18d100f3992e13b560f"
      },
      {
        "artist": "Bon Jovi",
        "track": "I’ll Be There For You",
        "spotify_artist": "Bon Jovi",
        "spotify_track": "I'll Be There For You",
        "time_sig": 4,
        "tempo": 145.546,
        "valence": 0.254,
        "mode": 1,
        "key": 2,
        "energy": 0.801,
        "duration": 346387,
        "genres": [
          "album rock",
          "alternative rock",
          "classic rock",
          "glam metal",
          "hard rock",
          "heavy christmas",
          "mellow gold",
          "post-grunge",
          "rock",
          "soft rock"
        ],
        "popularity": 40,
        "preview": "https://p.scdn.co/mp3-preview/642db2ccc44e259deb43c9c78054475ce2409841"
      },
      {
        "artist": "Simply Red",
        "track": "If You Don’t Know Be By Now"
      },
      {
        "artist": "Madonna",
        "track": "Like A Prayer",
        "spotify_artist": "Madonna",
        "spotify_track": "Like A Prayer",
        "time_sig": 4,
        "tempo": 111.037,
        "valence": 0.272,
        "mode": 1,
        "key": 5,
        "energy": 0.842,
        "duration": 342680,
        "genres": [
          "dance pop",
          "europop",
          "new wave pop",
          "pop",
          "pop rock",
          "post-teen pop",
          "urban contemporary"
        ],
        "popularity": 64,
        "preview": "https://p.scdn.co/mp3-preview/b56a70770267b00ccae13c2e8c8a34ed54627d02"
      },
      {
        "artist": "New Kids On The Block",
        "track": "I’ll Be Loving You (Forever)",
        "spotify_artist": "New Kids On The Block",
        "spotify_track": "I'll Be Loving You (Forever)",
        "time_sig": 4,
        "tempo": 134.706,
        "valence": 0.315,
        "mode": 1,
        "key": 11,
        "energy": 0.282,
        "duration": 263933,
        "genres": [
          "boy band",
          "dance pop",
          "pop",
          "pop christmas",
          "post-teen pop",
          "r&b",
          "soul christmas"
        ],
        "popularity": 42,
        "preview": "https://p.scdn.co/mp3-preview/c0e594fe46cd4af84ac3057419627c5abd785198"
      },
      {
        "artist": "Breathe",
        "track": "How Can I Fall?",
        "spotify_artist": "Breathe",
        "spotify_track": "How Can I Fall?",
        "time_sig": 4,
        "tempo": 132.195,
        "valence": 0.506,
        "mode": 1,
        "key": 9,
        "energy": 0.417,
        "duration": 284360,
        "genres": [

        ],
        "popularity": 42,
        "preview": "https://p.scdn.co/mp3-preview/bf851cbbe5130d92412c80a06e85b18bfef7aa45"
      },
      {
        "artist": "Milli Vanilli",
        "track": "Baby Don’t Forget My Number",
        "spotify_artist": "Milli Vanilli",
        "spotify_track": "Baby Don't Forget My Number",
        "time_sig": 4,
        "tempo": 100.313,
        "valence": 0.847,
        "mode": 0,
        "key": 6,
        "energy": 0.876,
        "duration": 249467,
        "genres": [
          "boy band",
          "freestyle",
          "new wave pop"
        ],
        "popularity": 30,
        "preview": "https://p.scdn.co/mp3-preview/4925be5799775412e0fdc7463a1fc8e0ea968ad7"
      },
      {
        "artist": "Martika",
        "track": "Toy Solider"
      },
      {
        "artist": "Paula Abdul",
        "track": "Forever Your Girl.",
        "spotify_artist": "Paula Abdul",
        "spotify_track": "Forever Your Girl",
        "time_sig": 4,
        "tempo": 119.966,
        "valence": 0.733,
        "mode": 1,
        "key": 2,
        "energy": 0.891,
        "duration": 299073,
        "genres": [
          "dance pop",
          "dance rock",
          "freestyle",
          "new romantic",
          "new wave",
          "new wave pop",
          "soft rock",
          "urban contemporary"
        ],
        "popularity": 33,
        "preview": "https://p.scdn.co/mp3-preview/5502f7be6c51d1d029343563ea301849e0b4d5d0"
      },
      {
        "artist": "Mike and The Mechanics",
        "track": "The Living Years",
        "spotify_artist": "Mike & The Mechanics",
        "spotify_track": "Living Years",
        "time_sig": 4,
        "tempo": 97.63,
        "valence": 0.31,
        "mode": 1,
        "key": 8,
        "energy": 0.417,
        "duration": 330267,
        "genres": [
          "album rock",
          "art rock",
          "dance rock",
          "mellow gold",
          "new romantic",
          "new wave",
          "new wave pop",
          "soft rock"
        ],
        "popularity": 38,
        "preview": "https://p.scdn.co/mp3-preview/db90d395f3e98413d2cd0a7b49f702ee78e55e12"
      },
      {
        "artist": "The Bangles",
        "track": "Eternal Flame",
        "spotify_artist": "The Bangles",
        "spotify_track": "Eternal Flame",
        "time_sig": 3,
        "tempo": 78.988,
        "valence": 0.383,
        "mode": 0,
        "key": 4,
        "energy": 0.358,
        "duration": 238027,
        "genres": [
          "dance rock",
          "jangle pop",
          "mellow gold",
          "new romantic",
          "new wave",
          "new wave pop",
          "soft rock",
          "synthpop"
        ],
        "popularity": 62,
        "preview": "https://p.scdn.co/mp3-preview/c558bc461278efa0159e732a1eb8e314ed1758f9"
      },
      {
        "artist": "Tone Loc",
        "track": "Wild Thing",
        "spotify_artist": "Tone-Loc",
        "spotify_track": "Wild Thing",
        "time_sig": 4,
        "tempo": 125.507,
        "valence": 0.827,
        "mode": 1,
        "key": 7,
        "energy": 0.673,
        "duration": 263573,
        "genres": [
          "hip hop",
          "hip house",
          "rap"
        ],
        "popularity": 45,
        "preview": "https://p.scdn.co/mp3-preview/9db7d085f76dcfedaa2cc600e8a3d6c8a2757f74"
      },
      {
        "artist": "Bad English",
        "track": "When I See You Smile",
        "spotify_artist": "Bad English",
        "spotify_track": "When I See You Smile",
        "time_sig": 4,
        "tempo": 135.671,
        "valence": 0.324,
        "mode": 1,
        "key": 7,
        "energy": 0.609,
        "duration": 257440,
        "genres": [
          "album rock",
          "glam metal",
          "hard rock",
          "mellow gold",
          "rock",
          "soft rock"
        ],
        "popularity": 49,
        "preview": "https://p.scdn.co/mp3-preview/fcd83dd2cfd6bf78eadb6aa586eeb30081cf86d0"
      },
      {
        "artist": "Cher",
        "track": "If I Could Turn Back Time",
        "spotify_artist": "Cher",
        "spotify_track": "If I Could Turn Back Time",
        "time_sig": 4,
        "tempo": 108.293,
        "valence": 0.516,
        "mode": 1,
        "key": 11,
        "energy": 0.566,
        "duration": 239827,
        "genres": [
          "adult standards",
          "dance pop",
          "dance rock",
          "disco",
          "hollywood",
          "mellow gold",
          "new wave pop",
          "pop",
          "pop christmas",
          "pop rock",
          "soft rock"
        ],
        "popularity": 51,
        "preview": "https://p.scdn.co/mp3-preview/b94befc5945cfe1a34864831a299c94bcb169bed"
      },
      {
        "artist": "Neneh Cherry",
        "track": "Buffalo Stance",
        "spotify_artist": "Neneh Cherry",
        "spotify_track": "Buffalo Stance - 12'' Version",
        "time_sig": 4,
        "tempo": 107.248,
        "valence": 0.773,
        "mode": 1,
        "key": 1,
        "energy": 0.627,
        "duration": 342360,
        "genres": [
          "dance rock",
          "europop",
          "hip house",
          "new romantic",
          "new wave pop",
          "urban contemporary"
        ],
        "popularity": 43,
        "preview": "https://p.scdn.co/mp3-preview/b8e866ef6208dfe17f53ac2d551cc4d1c80d2ae1"
      },
      {
        "artist": "Sheriff",
        "track": "When I’m With You",
        "spotify_artist": "Sheriff",
        "spotify_track": "When I'm With You",
        "time_sig": 4,
        "tempo": 135.786,
        "valence": 0.116,
        "mode": 1,
        "key": 9,
        "energy": 0.324,
        "duration": 238040,
        "genres": [
          "album rock",
          "glam metal",
          "hard rock"
        ],
        "popularity": 39,
        "preview": "https://p.scdn.co/mp3-preview/ad093e19dc2e9e6f31bb5dfdec76c1583a985244"
      },
      {
        "artist": "Taylor Dayne",
        "track": "Don’t Rush Me",
        "spotify_artist": "Taylor Dayne",
        "spotify_track": "Don't Rush Me",
        "time_sig": 4,
        "tempo": 130.591,
        "valence": 0.966,
        "mode": 0,
        "key": 7,
        "energy": 0.884,
        "duration": 227667,
        "genres": [
          "disco",
          "freestyle",
          "new wave pop",
          "soft rock"
        ],
        "popularity": 23,
        "preview": "https://p.scdn.co/mp3-preview/095b85ae67c670ce9a36a15f10916badad005f26"
      },
      {
        "artist": "Bon Jovi",
        "track": "Born To Be My Baby",
        "spotify_artist": "Bon Jovi",
        "spotify_track": "Born To Be My Baby",
        "time_sig": 4,
        "tempo": 131.275,
        "valence": 0.76,
        "mode": 1,
        "key": 7,
        "energy": 0.958,
        "duration": 280107,
        "genres": [
          "album rock",
          "alternative rock",
          "classic rock",
          "glam metal",
          "hard rock",
          "heavy christmas",
          "mellow gold",
          "post-grunge",
          "rock",
          "soft rock"
        ],
        "popularity": 39,
        "preview": "https://p.scdn.co/mp3-preview/5534355870eca8015fe06911ca8fc208c1ebfa6c"
      },
      {
        "artist": "Fine Young Cannibals",
        "track": "Good Thing",
        "spotify_artist": "Fine Young Cannibals",
        "spotify_track": "Good Thing",
        "time_sig": 4,
        "tempo": 164.718,
        "valence": 0.901,
        "mode": 0,
        "key": 9,
        "energy": 0.586,
        "duration": 201867,
        "genres": [
          "art rock",
          "dance rock",
          "mellow gold",
          "new romantic",
          "new wave",
          "new wave pop",
          "soft rock",
          "synthpop"
        ],
        "popularity": 50,
        "preview": "https://p.scdn.co/mp3-preview/d4b04778f1c09aeea70f3bae23b4baf3ee846466"
      },
      {
        "artist": "Sheena Easton",
        "track": "The Lover In Me",
        "spotify_artist": "Sheena Easton",
        "spotify_track": "The Lover In Me",
        "time_sig": 4,
        "tempo": 115.207,
        "valence": 0.934,
        "mode": 0,
        "key": 7,
        "energy": 0.811,
        "duration": 301373,
        "genres": [
          "dance rock",
          "disco",
          "freestyle",
          "mellow gold",
          "new romantic",
          "new wave pop",
          "soft rock",
          "soul christmas"
        ],
        "popularity": 16,
        "preview": "https://p.scdn.co/mp3-preview/196dfa1422bcc9c552d98153341328d76f1de398"
      },
      {
        "artist": "Young M.C.",
        "track": "Bust A Move",
        "spotify_artist": "Young MC",
        "spotify_track": "Bust A Move",
        "time_sig": 4,
        "tempo": 116.962,
        "valence": 0.731,
        "mode": 0,
        "key": 4,
        "energy": 0.77,
        "duration": 263914,
        "genres": [
          "gangster rap",
          "hip hop",
          "hip house",
          "rap"
        ],
        "popularity": 53,
        "preview": "https://p.scdn.co/mp3-preview/d71f975d36547201843a4f4ca55e004973423987"
      },
      {
        "artist": "Great White",
        "track": "Once Bitten, Twice Shy",
        "spotify_artist": "Great White",
        "spotify_track": "Once Bitten Twice Shy",
        "time_sig": 4,
        "tempo": 131.675,
        "valence": 0.611,
        "mode": 1,
        "key": 0,
        "energy": 0.541,
        "duration": 322933,
        "genres": [
          "album rock",
          "classic rock",
          "glam metal",
          "hard rock",
          "heavy christmas",
          "metal",
          "rock"
        ],
        "popularity": 47,
        "preview": "https://p.scdn.co/mp3-preview/f9b97778f85ceeb9c15de3a3def339e75518b7cb"
      },
      {
        "artist": "Prince",
        "track": "Batdance"
      },
      {
        "artist": "Michael Damian",
        "track": "Rock On",
        "spotify_artist": "Michael Damian",
        "spotify_track": "Rock On - Ver. 09",
        "time_sig": 4,
        "tempo": 168.247,
        "valence": 0.557,
        "mode": 0,
        "key": 1,
        "energy": 0.798,
        "duration": 212348,
        "genres": [
          "freestyle"
        ],
        "popularity": 23,
        "preview": "https://p.scdn.co/mp3-preview/0e9ed3c215791366fa7e0ded63e517d7707010c3"
      },
      {
        "artist": "Jody Watley",
        "track": "Real Love",
        "spotify_artist": "Jody Watley",
        "spotify_track": "Real Love",
        "time_sig": 4,
        "tempo": 109.191,
        "valence": 0.691,
        "mode": 1,
        "key": 7,
        "energy": 0.786,
        "duration": 264173,
        "genres": [
          "disco",
          "freestyle",
          "funk",
          "new jack swing",
          "post-disco",
          "quiet storm",
          "urban contemporary"
        ],
        "popularity": 27,
        "preview": "https://p.scdn.co/mp3-preview/1aa0ff229cd3661714bfbef7bb2ba675a40fb653"
      },
      {
        "artist": "B-52’s",
        "track": "Love Shack"
      },
      {
        "artist": "Bobby Brown",
        "track": "Every Little Step",
        "spotify_artist": "Bobby Brown",
        "spotify_track": "Every Little Step",
        "time_sig": 4,
        "tempo": 99.828,
        "valence": 0.943,
        "mode": 1,
        "key": 1,
        "energy": 0.656,
        "duration": 237240,
        "genres": [
          "funk",
          "hip pop",
          "new jack swing",
          "quiet storm",
          "r&b",
          "urban contemporary"
        ],
        "popularity": 48,
        "preview": "https://p.scdn.co/mp3-preview/c406f18716dba3aebde4d7212e3dda7ecd022fcf"
      },
      {
        "artist": "New Kids On The Block",
        "track": "Hangin’ Tough",
        "spotify_artist": "New Kids On The Block",
        "spotify_track": "Hangin' Tough",
        "time_sig": 4,
        "tempo": 90.775,
        "valence": 0.756,
        "mode": 1,
        "key": 6,
        "energy": 0.551,
        "duration": 256560,
        "genres": [
          "boy band",
          "dance pop",
          "pop",
          "pop christmas",
          "post-teen pop",
          "r&b",
          "soul christmas"
        ],
        "popularity": 40,
        "preview": "https://p.scdn.co/mp3-preview/7f47e9eefcbe1c5c5ac5b20b759f05271d06bbaa"
      },
      {
        "artist": "Rod Stewart",
        "track": "My Heart Can’t Tell You No"
      },
      {
        "artist": "Love and Rockets",
        "track": "So Alive",
        "spotify_artist": "Love and Rockets",
        "spotify_track": "So Alive",
        "time_sig": 4,
        "tempo": 118.829,
        "valence": 0.914,
        "mode": 1,
        "key": 10,
        "energy": 0.569,
        "duration": 257827,
        "genres": [
          "dance rock",
          "dream pop",
          "gothic rock",
          "jangle pop",
          "neo-psychedelic",
          "new romantic",
          "new wave",
          "post-punk",
          "uk post-punk"
        ],
        "popularity": 42,
        "preview": "https://p.scdn.co/mp3-preview/591a411a7e0791dd2ffcd65d26850c27a98af5af"
      },
      {
        "artist": "New Kids On The Block",
        "track": "You Got It (The Right Stuff)",
        "spotify_artist": "New Kids On The Block",
        "spotify_track": "You Got It (The Right Stuff)",
        "time_sig": 4,
        "tempo": 111.493,
        "valence": 0.869,
        "mode": 1,
        "key": 1,
        "energy": 0.687,
        "duration": 250747,
        "genres": [
          "boy band",
          "dance pop",
          "pop",
          "pop christmas",
          "post-teen pop",
          "r&b",
          "soul christmas"
        ],
        "popularity": 50,
        "preview": "https://p.scdn.co/mp3-preview/7e54019caa090b42151fb2c5fed2e82b90b8a017"
      },
      {
        "artist": "Def Leppard",
        "track": "Armageddon It",
        "spotify_artist": "Def Leppard",
        "spotify_track": "Armageddon It",
        "time_sig": 4,
        "tempo": 121.054,
        "valence": 0.342,
        "mode": 1,
        "key": 11,
        "energy": 0.928,
        "duration": 326653,
        "genres": [
          "album rock",
          "blues-rock",
          "classic rock",
          "glam metal",
          "hard rock",
          "mellow gold",
          "metal",
          "rock"
        ],
        "popularity": 39,
        "preview": "https://p.scdn.co/mp3-preview/1f35da58f6fa542741f76c6f10fd30b1d95e6c52"
      },
      {
        "artist": "Richard Marx",
        "track": "Satisfied",
        "spotify_artist": "Richard Marx",
        "spotify_track": "Satisfied",
        "time_sig": 4,
        "tempo": 108.991,
        "valence": 0.838,
        "mode": 1,
        "key": 8,
        "energy": 0.914,
        "duration": 254467,
        "genres": [
          "adult standards",
          "album rock",
          "mellow gold",
          "new romantic",
          "new wave pop",
          "rock",
          "soft rock"
        ],
        "popularity": 28,
        "preview": "https://p.scdn.co/mp3-preview/dac85a884d72dc663733b38e55598ce605d85042"
      },
      {
        "artist": "Madonna",
        "track": "Express Yourself",
        "spotify_artist": "Madonna",
        "spotify_track": "Express Yourself",
        "time_sig": 4,
        "tempo": 115.496,
        "valence": 0.631,
        "mode": 1,
        "key": 7,
        "energy": 0.765,
        "duration": 244173,
        "genres": [
          "dance pop",
          "europop",
          "new wave pop",
          "pop",
          "pop rock",
          "post-teen pop",
          "urban contemporary"
        ],
        "popularity": 48,
        "preview": "https://p.scdn.co/mp3-preview/36f0a211dd8aa0d63da6e2a61af445b1fbe5ca6b"
      },
      {
        "artist": "Dino",
        "track": "I Like It",
        "spotify_artist": "Dino",
        "spotify_track": "I Like It",
        "time_sig": 4,
        "tempo": 108.285,
        "valence": 0.936,
        "mode": 0,
        "key": 4,
        "energy": 0.667,
        "duration": 307200,
        "genres": [

        ],
        "popularity": 16,
        "preview": "https://p.scdn.co/mp3-preview/25380d05fff8894e823b4f3edfcdb9f05b18848c"
      },
      {
        "artist": "Donny Osmond",
        "track": "Soldier Of Love",
        "spotify_artist": "Donny Osmond",
        "spotify_track": "Soldier Of Love - 12\" Version",
        "time_sig": 4,
        "tempo": 192.6,
        "valence": 0.878,
        "mode": 0,
        "key": 10,
        "energy": 0.952,
        "duration": 353440,
        "genres": [
          "adult standards",
          "bubblegum pop",
          "mellow gold",
          "movie tunes",
          "soft rock"
        ],
        "popularity": 21,
        "preview": "https://p.scdn.co/mp3-preview/72fd016ffd5962c58bfb29e95e59565109662326"
      },
      {
        "artist": "Tears For Fears",
        "track": "Sowing The Seeds Of Love",
        "spotify_artist": "Tears For Fears",
        "spotify_track": "Sowing The Seeds Of Love",
        "time_sig": 4,
        "tempo": 174.472,
        "valence": 0.705,
        "mode": 1,
        "key": 0,
        "energy": 0.793,
        "duration": 376733,
        "genres": [
          "album rock",
          "art rock",
          "dance rock",
          "mellow gold",
          "new romantic",
          "new wave",
          "new wave pop",
          "permanent wave",
          "soft rock",
          "synthpop"
        ],
        "popularity": 45,
        "preview": "https://p.scdn.co/mp3-preview/087d69cb8a1f31b7e4b4a5060b50c6ae7480fbd7"
      },
      {
        "artist": "Madonna",
        "track": "Cherish",
        "spotify_artist": "Madonna",
        "spotify_track": "Cherish",
        "time_sig": 4,
        "tempo": 131.877,
        "valence": 0.906,
        "mode": 1,
        "key": 2,
        "energy": 0.875,
        "duration": 229600,
        "genres": [
          "dance pop",
          "europop",
          "new wave pop",
          "pop",
          "pop rock",
          "post-teen pop",
          "urban contemporary"
        ],
        "popularity": 41,
        "preview": "https://p.scdn.co/mp3-preview/a54cc01ec87efece613d618cdaba663ee3f8440a"
      },
      {
        "artist": "White Lion",
        "track": "When The Children Cry",
        "spotify_artist": "White Lion",
        "spotify_track": "When The Children Cry",
        "time_sig": 4,
        "tempo": 130.341,
        "valence": 0.374,
        "mode": 0,
        "key": 4,
        "energy": 0.236,
        "duration": 258547,
        "genres": [
          "album rock",
          "glam metal",
          "hard rock",
          "metal",
          "rock"
        ],
        "popularity": 48,
        "preview": "https://p.scdn.co/mp3-preview/a600fa52cce4a4d16cd78351dc3a0a18d243e580"
      },
      {
        "artist": "Skid Row",
        "track": "18 And Life",
        "spotify_artist": "Skid Row",
        "spotify_track": "18 And Life",
        "time_sig": 4,
        "tempo": 90.382,
        "valence": 0.378,
        "mode": 0,
        "key": 1,
        "energy": 0.753,
        "duration": 231133,
        "genres": [
          "album rock",
          "classic rock",
          "glam metal",
          "hard rock",
          "heavy christmas",
          "metal",
          "rock"
        ],
        "popularity": 56,
        "preview": "https://p.scdn.co/mp3-preview/55f24dd015afaeb11129ba2d9556caed7e927ee6"
      },
      {
        "artist": "Duran Duran",
        "track": "I Don’t Want Your Love",
        "spotify_artist": "Duran Duran",
        "spotify_track": "I Don't Want Your Love",
        "time_sig": 4,
        "tempo": 108.977,
        "valence": 0.886,
        "mode": 1,
        "key": 0,
        "energy": 0.723,
        "duration": 246427,
        "genres": [
          "album rock",
          "art rock",
          "dance rock",
          "europop",
          "mellow gold",
          "new romantic",
          "new wave",
          "new wave pop",
          "soft rock",
          "synthpop"
        ],
        "popularity": 16,
        "preview": "https://p.scdn.co/mp3-preview/aa82c7ec9c24c8b6cd5497f265150592a54ca5be"
      },
      {
        "artist": ".38 Special",
        "track": "Second Chances"
      },
      {
        "artist": "Karyn White",
        "track": "The Way You Love Me",
        "spotify_artist": "Karyn White",
        "spotify_track": "The Way You Love Me",
        "time_sig": 4,
        "tempo": 105.072,
        "valence": 0.87,
        "mode": 1,
        "key": 6,
        "energy": 0.785,
        "duration": 294720,
        "genres": [
          "freestyle",
          "neo soul",
          "new jack swing",
          "quiet storm",
          "r&b",
          "urban contemporary"
        ],
        "popularity": 32,
        "preview": "https://p.scdn.co/mp3-preview/387cd51410977075c3144cafd64f93f96e7defaa"
      },
      {
        "artist": "Tone Loc",
        "track": "Funky Cold Medina",
        "spotify_artist": "Tone-Loc",
        "spotify_track": "Funky Cold Medina",
        "time_sig": 4,
        "tempo": 117.497,
        "valence": 0.918,
        "mode": 0,
        "key": 5,
        "energy": 0.629,
        "duration": 248160,
        "genres": [
          "hip hop",
          "hip house",
          "rap"
        ],
        "popularity": 43,
        "preview": "https://p.scdn.co/mp3-preview/a920bb65f40272699284fc0b70f06ed060572928"
      },
      {
        "artist": "Bangles",
        "track": "In Your Room",
        "spotify_artist": "The Bangles",
        "spotify_track": "In Your Room",
        "time_sig": 4,
        "tempo": 149.29,
        "valence": 0.765,
        "mode": 1,
        "key": 0,
        "energy": 0.76,
        "duration": 209773,
        "genres": [
          "dance rock",
          "jangle pop",
          "mellow gold",
          "new romantic",
          "new wave",
          "new wave pop",
          "soft rock",
          "synthpop"
        ],
        "popularity": 37,
        "preview": "https://p.scdn.co/mp3-preview/663e35b0cbed06e87f1188cc0f8d9cbe88e4a5ec"
      },
      {
        "artist": "Natalie Cole",
        "track": "Miss You Like Crazy",
        "spotify_artist": "Natalie Cole",
        "spotify_track": "Miss You Like Crazy",
        "time_sig": 4,
        "tempo": 131.123,
        "valence": 0.257,
        "mode": 1,
        "key": 2,
        "energy": 0.546,
        "duration": 234280,
        "genres": [
          "adult standards",
          "brill building pop",
          "cabaret",
          "christmas",
          "classic funk rock",
          "disco",
          "jazz blues",
          "jazz christmas",
          "lounge",
          "mellow gold",
          "motown",
          "quiet storm",
          "soul",
          "soul blues",
          "soul christmas",
          "vocal jazz"
        ],
        "popularity": 31,
        "preview": "https://p.scdn.co/mp3-preview/475b79eb12234ca053786683ec12a18fc7c265a8"
      },
      {
        "artist": "Cure",
        "track": "Love Song",
        "spotify_artist": "The Cure",
        "spotify_track": "Love Song",
        "time_sig": 4,
        "tempo": 139.932,
        "valence": 0.755,
        "mode": 0,
        "key": 9,
        "energy": 0.865,
        "duration": 208000,
        "genres": [
          "alternative rock",
          "art rock",
          "dance rock",
          "funk rock",
          "indie rock",
          "new romantic",
          "new wave",
          "new wave pop",
          "permanent wave",
          "rock",
          "uk post-punk"
        ],
        "popularity": 41,
        "preview": "https://p.scdn.co/mp3-preview/42bf15b98700808aa4114c0b6a177f35585bf97e"
      },
      {
        "artist": "Karyn White",
        "track": "Secret Rendesvous"
      },
      {
        "artist": "Jeff Healey Band",
        "track": "Angel Eyes",
        "spotify_artist": "The Jeff Healey Band",
        "spotify_track": "Angel Eyes",
        "time_sig": 4,
        "tempo": 126.909,
        "valence": 0.393,
        "mode": 1,
        "key": 0,
        "energy": 0.571,
        "duration": 280933,
        "genres": [
          "blues-rock",
          "british blues",
          "classic rock",
          "electric blues",
          "modern blues",
          "southern rock",
          "texas blues"
        ],
        "popularity": 41,
        "preview": "https://p.scdn.co/mp3-preview/a871cdfd14e334c49be248c5af2d38435f04bdc3"
      },
      {
        "artist": "Guns N’ Roses",
        "track": "Patience",
        "spotify_artist": "Guns N' Roses",
        "spotify_track": "Patience",
        "time_sig": 4,
        "tempo": 120.316,
        "valence": 0.366,
        "mode": 1,
        "key": 6,
        "energy": 0.266,
        "duration": 356293,
        "genres": [
          "album rock",
          "alternative metal",
          "alternative rock",
          "classic rock",
          "funk rock",
          "glam metal",
          "hard rock",
          "post-grunge",
          "rock"
        ],
        "popularity": 55,
        "preview": "https://p.scdn.co/mp3-preview/8f0df3ccce0b339a98167eb030b913e9bc74a03b"
      },
      {
        "artist": "Eddie Money",
        "track": "Walk On Water",
        "spotify_artist": "Eddie Money",
        "spotify_track": "Walk On Water",
        "time_sig": 4,
        "tempo": 118.966,
        "valence": 0.564,
        "mode": 1,
        "key": 2,
        "energy": 0.931,
        "duration": 279027,
        "genres": [
          "album rock",
          "classic rock",
          "dance rock",
          "glam metal",
          "hard rock",
          "mellow gold",
          "new wave pop",
          "rock",
          "soft rock",
          "southern rock"
        ],
        "popularity": 32,
        "preview": "https://p.scdn.co/mp3-preview/204b96c80e6c02e47849bbd85a07acec86a1d752"
      },
      {
        "artist": "New Kids On The Block",
        "track": "Cover Girl",
        "spotify_artist": "New Kids On The Block",
        "spotify_track": "Cover Girl",
        "time_sig": 4,
        "tempo": 119.948,
        "valence": 0.956,
        "mode": 1,
        "key": 6,
        "energy": 0.765,
        "duration": 241840,
        "genres": [
          "boy band",
          "dance pop",
          "pop",
          "pop christmas",
          "post-teen pop",
          "r&b",
          "soul christmas"
        ],
        "popularity": 30,
        "preview": "https://p.scdn.co/mp3-preview/2463cf7f381b0932357661319c6b0c12274472f7"
      },
      {
        "artist": "Guns N’ Roses",
        "track": "Welcom To The Jungle"
      },
      {
        "artist": "Surface",
        "track": "Shower Me With Your Love",
        "spotify_artist": "Surface",
        "spotify_track": "Shower Me With Your Love",
        "time_sig": 4,
        "tempo": 131.28,
        "valence": 0.191,
        "mode": 1,
        "key": 9,
        "energy": 0.356,
        "duration": 294960,
        "genres": [
          "funk",
          "j-poprock",
          "new jack swing",
          "quiet storm",
          "urban contemporary"
        ],
        "popularity": 31,
        "preview": "https://p.scdn.co/mp3-preview/6cc49bc1838fc4c030a7dccc5f7d6f3acf8ec498"
      },
      {
        "artist": "R.E.M.",
        "track": "Stand",
        "spotify_artist": "R.E.M.",
        "spotify_track": "Stand",
        "time_sig": 4,
        "tempo": 109.319,
        "valence": 0.915,
        "mode": 1,
        "key": 4,
        "energy": 0.863,
        "duration": 192173,
        "genres": [
          "album rock",
          "alternative rock",
          "art rock",
          "classic rock",
          "dance rock",
          "folk christmas",
          "folk-pop",
          "indie rock",
          "mellow gold",
          "new wave",
          "new wave pop",
          "permanent wave",
          "pop christmas",
          "pop rock",
          "post-grunge",
          "rock",
          "singer-songwriter"
        ],
        "popularity": 25,
        "preview": "https://p.scdn.co/mp3-preview/4dcea57bfc9604998ff6e3d3651be6db236719ed"
      },
      {
        "artist": "Lita Ford",
        "track": "Close My Eyes Forever",
        "spotify_artist": "Lita Ford",
        "spotify_track": "Close My Eyes Forever",
        "time_sig": 4,
        "tempo": 130.574,
        "valence": 0.238,
        "mode": 1,
        "key": 5,
        "energy": 0.331,
        "duration": 283133,
        "genres": [
          "album rock",
          "classic rock",
          "glam metal",
          "hard rock",
          "metal",
          "rock",
          "sleaze rock"
        ],
        "popularity": 50,
        "preview": "https://p.scdn.co/mp3-preview/19c5e02fd234d9aa92b41ea265223ee50b10ff45"
      },
      {
        "artist": "Tiffany",
        "track": "All This Time",
        "spotify_artist": "Tiffany",
        "spotify_track": "All This Time",
        "time_sig": 4,
        "tempo": 179.525,
        "valence": 0.494,
        "mode": 1,
        "key": 1,
        "energy": 0.511,
        "duration": 263227,
        "genres": [
          "pop christmas",
          "soul christmas"
        ],
        "popularity": 24,
        "preview": "https://p.scdn.co/mp3-preview/1e632aaa2a06de4e3042490d84c7948977ba1f54"
      },
      {
        "artist": "Cher and Peter Cetera",
        "track": "After All",
        "spotify_artist": "Musical Creations Karaoke",
        "spotify_track": "After All (Originally Performed by Peter Cetera & Cher) [Vocal Version]",
        "time_sig": 4,
        "tempo": 71.174,
        "valence": 0.118,
        "mode": 1,
        "key": 4,
        "energy": 0.335,
        "duration": 233734,
        "genres": [

        ],
        "popularity": 5,
        "preview": "https://p.scdn.co/mp3-preview/955af6cbfe5a1fdd7102e0025729b908f74eee03"
      },
      {
        "artist": "Bobby Brown",
        "track": "Roni",
        "spotify_artist": "Bobby Brown",
        "spotify_track": "Roni",
        "time_sig": 4,
        "tempo": 146.658,
        "valence": 0.905,
        "mode": 1,
        "key": 9,
        "energy": 0.696,
        "duration": 358333,
        "genres": [
          "funk",
          "hip pop",
          "new jack swing",
          "quiet storm",
          "r&b",
          "urban contemporary"
        ],
        "popularity": 43,
        "preview": "https://p.scdn.co/mp3-preview/9c753e1952e5efa50d5a159a78f2a5b150a8f244"
      },
      {
        "artist": "Aerosmith",
        "track": "Love In An Elevator",
        "spotify_artist": "Aerosmith",
        "spotify_track": "Love In An Elevator",
        "time_sig": 4,
        "tempo": 93.703,
        "valence": 0.562,
        "mode": 1,
        "key": 4,
        "energy": 0.968,
        "duration": 322227,
        "genres": [
          "album rock",
          "alternative rock",
          "blues-rock",
          "classic rock",
          "hard rock",
          "mellow gold",
          "post-grunge",
          "rock",
          "soft rock"
        ],
        "popularity": 44,
        "preview": "https://p.scdn.co/mp3-preview/aa498149f0dce664c9eb8baaa4db8afa65f014f2"
      },
      {
        "artist": "Bon Jovi",
        "track": "Lay Your Hands On Me",
        "spotify_artist": "Bon Jovi",
        "spotify_track": "Lay Your Hands On Me",
        "time_sig": 4,
        "tempo": 100.578,
        "valence": 0.418,
        "mode": 1,
        "key": 2,
        "energy": 0.964,
        "duration": 229293,
        "genres": [
          "album rock",
          "alternative rock",
          "classic rock",
          "glam metal",
          "hard rock",
          "heavy christmas",
          "mellow gold",
          "post-grunge",
          "rock",
          "soft rock"
        ],
        "popularity": 34,
        "preview": "https://p.scdn.co/mp3-preview/275bffe4ad902529f0ec58b58198d5334c3246d1"
      },
      {
        "artist": "When In Rome",
        "track": "This Promise"
      },
      {
        "artist": "Edie Brickell and The New Bohemians",
        "track": "What I Am",
        "spotify_artist": "Edie Brickell & New Bohemians",
        "spotify_track": "What I Am",
        "time_sig": 4,
        "tempo": 177.841,
        "valence": 0.552,
        "mode": 1,
        "key": 2,
        "energy": 0.674,
        "duration": 297867,
        "genres": [
          "lilith",
          "new wave pop"
        ],
        "popularity": 43,
        "preview": "https://p.scdn.co/mp3-preview/c1be1d31d46f7635cf163a138970e4083b8bb108"
      },
      {
        "artist": "Boys Club",
        "track": "I Remember Holding You"
      },
      {
        "artist": "Guns N’ Roses",
        "track": "Paradise City",
        "spotify_artist": "Guns N' Roses",
        "spotify_track": "Paradise City",
        "time_sig": 4,
        "tempo": 100.346,
        "valence": 0.479,
        "mode": 1,
        "key": 11,
        "energy": 0.949,
        "duration": 406307,
        "genres": [
          "album rock",
          "alternative metal",
          "alternative rock",
          "classic rock",
          "funk rock",
          "glam metal",
          "hard rock",
          "post-grunge",
          "rock"
        ],
        "popularity": 66,
        "preview": "https://p.scdn.co/mp3-preview/b8995a30964d50cd30fccab54eb29d611e6b7d00"
      },
      {
        "artist": "Samantha Fox",
        "track": "Iwanna Have Some Fun"
      },
      {
        "artist": "Rick Astley",
        "track": "She Wants To Dance With Me",
        "spotify_artist": "Rick Astley",
        "spotify_track": "She Wants to Dance with Me",
        "time_sig": 4,
        "tempo": 118.031,
        "valence": 0.941,
        "mode": 1,
        "key": 6,
        "energy": 0.83,
        "duration": 196440,
        "genres": [
          "dance rock",
          "europop",
          "mellow gold",
          "new romantic",
          "new wave",
          "new wave pop",
          "soft rock",
          "synthpop"
        ],
        "popularity": 35,
        "preview": "https://p.scdn.co/mp3-preview/2c9559044a2e14dec775e8ba40bfe8da5ddc557d"
      },
      {
        "artist": "Vanessa Williams",
        "track": "Dreamin’",
        "spotify_artist": "Vanessa Williams",
        "spotify_track": "Dreamin'",
        "time_sig": 4,
        "tempo": 167.926,
        "valence": 0.454,
        "mode": 0,
        "key": 1,
        "energy": 0.454,
        "duration": 327280,
        "genres": [
          "freestyle",
          "new jack swing",
          "pop christmas",
          "quiet storm",
          "r&b",
          "soul christmas",
          "urban contemporary"
        ],
        "popularity": 29,
        "preview": "https://p.scdn.co/mp3-preview/b954abc09da1d77050bf00e7f902b8138a0e024b"
      },
      {
        "artist": "Babyface",
        "track": "It’s No Crime",
        "spotify_artist": "Babyface",
        "spotify_track": "It's No Crime",
        "time_sig": 4,
        "tempo": 116.316,
        "valence": 0.907,
        "mode": 1,
        "key": 2,
        "energy": 0.802,
        "duration": 241493,
        "genres": [
          "dance pop",
          "hip pop",
          "neo soul",
          "new jack swing",
          "pop christmas",
          "quiet storm",
          "r&b",
          "soul christmas",
          "urban contemporary"
        ],
        "popularity": 28,
        "preview": "https://p.scdn.co/mp3-preview/48ce9008d5b62a15051b6336c900e383f5bbfb6f"
      },
      {
        "artist": "Alice Cooper",
        "track": "Poison",
        "spotify_artist": "Alice Cooper",
        "spotify_track": "Poison",
        "time_sig": 4,
        "tempo": 118.668,
        "valence": 0.271,
        "mode": 0,
        "key": 2,
        "energy": 0.865,
        "duration": 269627,
        "genres": [
          "album rock",
          "alternative rock",
          "blues-rock",
          "classic rock",
          "glam metal",
          "glam rock",
          "hard rock",
          "heavy christmas",
          "metal",
          "protopunk",
          "psychedelic rock",
          "rock",
          "southern rock"
        ],
        "popularity": 59,
        "preview": "https://p.scdn.co/mp3-preview/a466b4b3a0ce049185b4560bea3a3d7bc0517120"
      },
      {
        "artist": "Donna Summer",
        "track": "This Time I Know It’s For Real",
        "spotify_artist": "Donna Summer",
        "spotify_track": "This Time I Know It's for Real",
        "time_sig": 4,
        "tempo": 116.054,
        "valence": 0.857,
        "mode": 0,
        "key": 4,
        "energy": 0.866,
        "duration": 218960,
        "genres": [
          "adult standards",
          "classic funk rock",
          "dance pop",
          "dance rock",
          "disco",
          "europop",
          "funk",
          "mellow gold",
          "motown",
          "new romantic",
          "new wave pop",
          "quiet storm",
          "soft rock",
          "soul",
          "soul christmas"
        ],
        "popularity": 32,
        "preview": "https://p.scdn.co/mp3-preview/0acffd0438fb11ffc31d71d32ae4b2609dabda84"
      },
      {
        "artist": "Michael Jackson",
        "track": "Smooth Criminal",
        "spotify_artist": "Michael Jackson",
        "spotify_track": "Smooth Criminal - 2012 Remaster",
        "time_sig": 4,
        "tempo": 118.193,
        "valence": 0.588,
        "mode": 1,
        "key": 8,
        "energy": 0.981,
        "duration": 257760,
        "genres": [
          "dance pop",
          "funk rock",
          "mellow gold",
          "pop",
          "pop christmas",
          "r&b",
          "soft rock",
          "urban contemporary"
        ],
        "popularity": 60,
        "preview": "https://p.scdn.co/mp3-preview/8dcbe2702477ac98c7c711cbafcac43e10063949"
      },
      {
        "artist": "Deon Estus",
        "track": "Heavan Help Me"
      },
      {
        "artist": "Bobby Brown",
        "track": "Rock Wit’cha",
        "spotify_artist": "Bobby Brown",
        "spotify_track": "Rock Wit'cha",
        "time_sig": 4,
        "tempo": 77.506,
        "valence": 0.908,
        "mode": 0,
        "key": 11,
        "energy": 0.561,
        "duration": 289533,
        "genres": [
          "funk",
          "hip pop",
          "new jack swing",
          "quiet storm",
          "r&b",
          "urban contemporary"
        ],
        "popularity": 42,
        "preview": "https://p.scdn.co/mp3-preview/0d96f435fa7e9a83b5c3def8704416292c0d2ce7"
      },
      {
        "artist": "Sa-fire",
        "track": "Thinking Of You"
      },
      {
        "artist": "Expose",
        "track": "What You Don’t Know",
        "spotify_artist": "Exposé",
        "spotify_track": "What You Don't Know - Radio Mix",
        "time_sig": 4,
        "tempo": 119.594,
        "valence": 0.909,
        "mode": 0,
        "key": 3,
        "energy": 0.887,
        "duration": 252467,
        "genres": [
          "freestyle",
          "new wave pop",
          "soul christmas"
        ],
        "popularity": 17,
        "preview": "https://p.scdn.co/mp3-preview/eaaabb3fd5143985a40259a16b59ca2829451631"
      },
      {
        "artist": "Ann Wilson and Robin Zander",
        "track": "Surrender To Me",
        "spotify_artist": "Ameritz Countdown Karaoke",
        "spotify_track": "Surrender to Me (In the Style of Ann Wilson & Robin Zander) [Karaoke Version]",
        "time_sig": 4,
        "tempo": 74.982,
        "valence": 0.177,
        "mode": 0,
        "key": 11,
        "energy": 0.359,
        "duration": 242171,
        "genres": [

        ],
        "popularity": 2,
        "preview": "https://p.scdn.co/mp3-preview/39e66eb6adbc51d6b297a64ca37eedd855e024e5"
      },
      {
        "artist": "Don Henley",
        "track": "The End Of The Innocence",
        "spotify_artist": "Don Henley",
        "spotify_track": "The End Of The Innocence",
        "time_sig": 4,
        "tempo": 116.561,
        "valence": 0.385,
        "mode": 1,
        "key": 8,
        "energy": 0.424,
        "duration": 318200,
        "genres": [
          "album rock",
          "art rock",
          "classic rock",
          "dance rock",
          "folk",
          "folk rock",
          "hard rock",
          "mellow gold",
          "new romantic",
          "new wave pop",
          "rock",
          "roots rock",
          "singer-songwriter",
          "soft rock",
          "southern rock"
        ],
        "popularity": 45,
        "preview": "https://p.scdn.co/mp3-preview/2cef6b1896b777a99339707e6982c6990c1f3d0a"
      },
      {
        "artist": "Soul II Soul",
        "track": "Keep On Movin",
        "spotify_artist": "Soul II Soul",
        "spotify_track": "Keep On Movin' - feat. Caron Wheeler",
        "time_sig": 4,
        "tempo": 93.144,
        "valence": 0.69,
        "mode": 0,
        "key": 6,
        "energy": 0.47,
        "duration": 362600,
        "genres": [
          "classic funk rock",
          "disco",
          "funk",
          "hip house",
          "motown",
          "new jack swing",
          "post-disco",
          "quiet storm",
          "soul",
          "urban contemporary"
        ],
        "popularity": 42,
        "preview": "https://p.scdn.co/mp3-preview/8d382dfe9b061b5ea7555538b37bb6efc33cd2e1"
      }
    ]
  }
}
